asyncgram/__init__.py
asyncgram/client.py
asyncgram-0.0.4.dist-info/WHEEL
asyncgram-0.0.4.dist-info/METADATA
asyncgram-0.0.4.dist-info/RECORD
